[
  {
    "code": "class Solution {\npublic:\n    bool canWinNim(int n) {\n        return n%4? 1:0;\n    }\n};",
    "compare_result": "111111111111111111111111111111111111111111111111111111111111",
    "flag_type": 1,
    "frontend_id": 10,
    "has_notes": false,
    "id": 2050748387,
    "is_pending": "Not Pending",
    "lang": "cpp",
    "lang_name": "C++",
    "memory": "7.9 MB",
    "question_id": 292,
    "runtime": "0 ms",
    "status": 10,
    "status_display": "Accepted",
    "time": "2 days, 5 hours",
    "timestamp": 1782796415,
    "title": "Nim Game",
    "title_slug": "nim-game",
    "url": "/submissions/detail/2050748387/",
    "difficulty": "Easy",
    "topic_tags": [
      "math",
      "brainteaser",
      "game-theory"
    ]
  },
  {
    "code": "class Solution {\npublic:\n    int bulbSwitch(int n) {\n    return sqrt(n);\n    }\n};",
    "compare_result": "11111111111111111111111111111111111",
    "flag_type": 1,
    "frontend_id": 9,
    "has_notes": false,
    "id": 2050747569,
    "is_pending": "Not Pending",
    "lang": "cpp",
    "lang_name": "C++",
    "memory": "7.8 MB",
    "question_id": 319,
    "runtime": "0 ms",
    "status": 10,
    "status_display": "Accepted",
    "time": "2 days, 5 hours",
    "timestamp": 1782796373,
    "title": "Bulb Switcher",
    "title_slug": "bulb-switcher",
    "url": "/submissions/detail/2050747569/",
    "difficulty": "Medium",
    "topic_tags": [
      "math",
      "brainteaser"
    ]
  },
  {
    "code": "class Solution {\npublic:\n    bool xorGame(vector<int>& nums) {\n        int xr=0;\nfor (int i = 0; i < nums.size(); i++)\n{\n    xr ^= nums[i];\n}\n        return (xr == 0 || nums.size() % 2 == 0);\n    }\n};",
    "compare_result": "111111111111111111111111111111111111111111111111111111111111111111111111111111111111111111111111111111111111111111111111111111111111111111111111111111111111111111111111",
    "flag_type": 1,
    "frontend_id": 8,
    "has_notes": false,
    "id": 2050747265,
    "is_pending": "Not Pending",
    "lang": "cpp",
    "lang_name": "C++",
    "memory": "16.4 MB",
    "question_id": 828,
    "runtime": "0 ms",
    "status": 10,
    "status_display": "Accepted",
    "time": "2 days, 5 hours",
    "timestamp": 1782796357,
    "title": "Chalkboard XOR Game",
    "title_slug": "chalkboard-xor-game",
    "url": "/submissions/detail/2050747265/",
    "difficulty": "Hard",
    "topic_tags": [
      "array",
      "math",
      "bit-manipulation",
      "brainteaser",
      "game-theory"
    ]
  },
  {
    "code": "class Solution {\npublic:\n    bool divisorGame(int n) {\n        if(n % 2 == 0)\n    return true;\n       else\n    return false;\n    }\n};",
    "compare_result": "1111111111111111111111111111111111111111",
    "flag_type": 1,
    "frontend_id": 7,
    "has_notes": false,
    "id": 2050746970,
    "is_pending": "Not Pending",
    "lang": "cpp",
    "lang_name": "C++",
    "memory": "7.8 MB",
    "question_id": 1086,
    "runtime": "0 ms",
    "status": 10,
    "status_display": "Accepted",
    "time": "2 days, 5 hours",
    "timestamp": 1782796341,
    "title": "Divisor Game",
    "title_slug": "divisor-game",
    "url": "/submissions/detail/2050746970/",
    "difficulty": "Easy",
    "topic_tags": [
      "math",
      "dynamic-programming",
      "brainteaser",
      "game-theory"
    ]
  },
  {
    "code": "class Solution {\npublic:\n    double nthPersonGetsNthSeat(int n) {\n        return (n==1)? 1: 0.5;\n    }\n};",
    "compare_result": "1111111111111111111111111111111111111111111111111111111111111111111111111111111111111111111111111111",
    "flag_type": 1,
    "frontend_id": 6,
    "has_notes": false,
    "id": 2050746678,
    "is_pending": "Not Pending",
    "lang": "cpp",
    "lang_name": "C++",
    "memory": "8.1 MB",
    "question_id": 1362,
    "runtime": "0 ms",
    "status": 10,
    "status_display": "Accepted",
    "time": "2 days, 5 hours",
    "timestamp": 1782796325,
    "title": "Airplane Seat Assignment Probability",
    "title_slug": "airplane-seat-assignment-probability",
    "url": "/submissions/detail/2050746678/",
    "difficulty": "Medium",
    "topic_tags": [
      "math",
      "dynamic-programming",
      "brainteaser",
      "probability-and-statistics"
    ]
  },
  {
    "code": "class Solution {\npublic:\n    int getLastMoment(int n, vector<int>& left, vector<int>& right) {\n        int mxl= 0;\n        int mxr = 0;\n        for( int i = 0; i<left.size();i++){\n            if( mxl<left[i]){\n                mxl = left[i];\n            }\n        }\n                for( int i = 0; i<right.size();i++){\n            if( mxr<n-right[i]){\n                mxr =n-right[i];\n            }\n    }\n    return max(mxr,mxl);\n    }\n};",
    "compare_result": "11111111111111111111111111111111111111111111111111111111111111111111111111111111111111111111111111111111111111111111111111111111111111111111111111111111111111111111111",
    "flag_type": 1,
    "frontend_id": 5,
    "has_notes": false,
    "id": 2050746319,
    "is_pending": "Not Pending",
    "lang": "cpp",
    "lang_name": "C++",
    "memory": "26.8 MB",
    "question_id": 1627,
    "runtime": "0 ms",
    "status": 10,
    "status_display": "Accepted",
    "time": "2 days, 5 hours",
    "timestamp": 1782796307,
    "title": "Last Moment Before All Ants Fall Out of a Plank",
    "title_slug": "last-moment-before-all-ants-fall-out-of-a-plank",
    "url": "/submissions/detail/2050746319/",
    "difficulty": "Medium",
    "topic_tags": [
      "array",
      "brainteaser",
      "simulation"
    ]
  },
  {
    "code": "class Solution {\npublic:\n    int numberOfSubstrings(string s) {\n        int last[3] = {-1, -1, -1}, left = 0, count = 0;\n        for(int right = 0; right < s.size(); right++){\n            char c = s[right];\n            last[c - 'a'] = right;\n            if(last[0] != -1 && last[1] != -1 && last[2] != -1){\n                count += min({last[0], last[1], last[2]}) + 1;\n            }\n        }\n\n        return count;\n    }\n};",
    "compare_result": "111111111111111111111111111111111111111111111111111111",
    "flag_type": 1,
    "frontend_id": 4,
    "has_notes": null,
    "id": 2050744636,
    "is_pending": "Not Pending",
    "lang": "cpp",
    "lang_name": "C++",
    "memory": "11 MB",
    "question_id": 1460,
    "runtime": "3 ms",
    "status": 10,
    "status_display": "Accepted",
    "time": "2 days, 5 hours",
    "timestamp": 1782796220,
    "title": "Number of Substrings Containing All Three Characters",
    "title_slug": "number-of-substrings-containing-all-three-characters",
    "url": "/submissions/detail/2050744636/",
    "difficulty": "Medium",
    "topic_tags": [
      "hash-table",
      "string",
      "sliding-window"
    ]
  },
  {
    "code": "bool stoneGame(int* piles, int pilesSize) {\n    return true;\n}",
    "compare_result": "1111111111111111111111111111111111111111111111",
    "flag_type": 1,
    "frontend_id": 3,
    "has_notes": false,
    "id": 2050316306,
    "is_pending": "Not Pending",
    "lang": "c",
    "lang_name": "C",
    "memory": "8.7 MB",
    "question_id": 909,
    "runtime": "0 ms",
    "status": 10,
    "status_display": "Accepted",
    "time": "2 days, 17 hours",
    "timestamp": 1782751925,
    "title": "Stone Game",
    "title_slug": "stone-game",
    "url": "/submissions/detail/2050316306/",
    "difficulty": "Medium",
    "topic_tags": [
      "array",
      "math",
      "dynamic-programming",
      "game-theory"
    ]
  },
  {
    "code": "class Solution {\npublic:\n    bool stoneGame(vector<int>& piles) {\n        return true;\n    }\n};",
    "compare_result": "1111111111111111111111111111111111111111111111",
    "flag_type": 1,
    "frontend_id": 2,
    "has_notes": false,
    "id": 2050311245,
    "is_pending": "Not Pending",
    "lang": "cpp",
    "lang_name": "C++",
    "memory": "10.5 MB",
    "question_id": 909,
    "runtime": "0 ms",
    "status": 10,
    "status_display": "Accepted",
    "time": "2 days, 17 hours",
    "timestamp": 1782751685,
    "title": "Stone Game",
    "title_slug": "stone-game",
    "url": "/submissions/detail/2050311245/",
    "difficulty": "Medium",
    "topic_tags": [
      "array",
      "math",
      "dynamic-programming",
      "game-theory"
    ]
  },
  {
    "code": "class Solution {\npublic:\n    bool isStrictlyPalindromic(int n) {\n        return false;\n    }\n};",
    "compare_result": "1111111111111111111111111111111111111111111111111111111111111111111",
    "flag_type": 1,
    "frontend_id": 1,
    "has_notes": false,
    "id": 2050304148,
    "is_pending": "Not Pending",
    "lang": "cpp",
    "lang_name": "C++",
    "memory": "7.9 MB",
    "question_id": 2481,
    "runtime": "0 ms",
    "status": 10,
    "status_display": "Accepted",
    "time": "2 days, 17 hours",
    "timestamp": 1782751347,
    "title": "Strictly Palindromic Number",
    "title_slug": "strictly-palindromic-number",
    "url": "/submissions/detail/2050304148/",
    "difficulty": "Medium",
    "topic_tags": [
      "math",
      "two-pointers",
      "brainteaser"
    ]
  }
]